fastapi_app/__init__.py
fastapi_app/app.py
fastapi_app/static/index.html
fastapi_simple_app-0.1.1.dist-info/licenses/LICENSE
fastapi_simple_app-0.1.1.dist-info/METADATA
fastapi_simple_app-0.1.1.dist-info/WHEEL
fastapi_simple_app-0.1.1.dist-info/entry_points.txt
fastapi_simple_app-0.1.1.dist-info/top_level.txt
fastapi_simple_app-0.1.1.dist-info/RECORD
