Metadata-Version: 2.4
Name: fastapi_simple_app
Version: 0.1.1
Summary: Prosta aplikacja FastAPI
Home-page: https://github.com/twojprofil/fastapi_app
Author: Twoje Imię
Author-email: twoj@email.com
Classifier: Programming Language :: Python :: 3
Classifier: Framework :: FastAPI
Classifier: License :: OSI Approved :: MIT License
Classifier: Operating System :: OS Independent
Requires-Python: >=3.7
License-File: LICENSE
Requires-Dist: fastapi
Requires-Dist: uvicorn
Requires-Dist: pydantic
Dynamic: author
Dynamic: author-email
Dynamic: classifier
Dynamic: description
Dynamic: description-content-type
Dynamic: home-page
Dynamic: license-file
Dynamic: requires-dist
Dynamic: requires-python
Dynamic: summary
